<BOM_INB_IFD>
  <CTRL_SEG>
    <TRNNAM>BOM_TRAN</TRNNAM>
    <TRNVER>9.0</TRNVER>
    <WHSE_ID>WMD1</WHSE_ID>
    <HEADER_SEG>
       <SEGNAM>HEADER_SEG</SEGNAM>
       <TRNTYP>C</TRNTYP>
       <BOMNUM>BOMCYCLE01</BOMNUM>
       <CLIENT_ID>CLIENT A</CLIENT_ID>
       <PRTNUM>CYC_EA_PRT1</PRTNUM>
       <HSTSTS></HSTSTS>
       <LOTNUM></LOTNUM>
       <SUP_LOTNUM></SUP_LOTNUM>
       <REVLVL></REVLVL>
       <ORGCOD></ORGCOD>
       <MINQTY>300</MINQTY>
       <PRD_TOL_PCT></PRD_TOL_PCT>
       <BOMCOD>P</BOMCOD>
       <UNTDTE></UNTDTE>
       <PRCARE></PRCARE>
       <PRCLOC></PRCLOC>
       <DEFFLG>0</DEFFLG>
       <AUT_GEN_FLG>1</AUT_GEN_FLG>
       <CMP_TRK_FLG>1</CMP_TRK_FLG>
       <INVSTS>A</INVSTS>
       <MIN_CATCH_QTY></MIN_CATCH_QTY>
       <PRDLIN></PRDLIN>
       <EXCL_FLG>0</EXCL_FLG>
       <INVSTS_PRG>A</INVSTS_PRG>
       <NUM_PEOPLE></NUM_PEOPLE>
       <RPQFLG>0</RPQFLG>
       <SPEED></SPEED>
       <ACTCOD></ACTCOD>
       <XDKFLG>0</XDKFLG>
       <UNTCAS>1</UNTCAS>
       <UNTPAK>0</UNTPAK>
       <FTPCOD></FTPCOD>
       <OVRCOD></OVRCOD>
       <OVRAMT>0</OVRAMT>
       <ORDINV></ORDINV>
       <MIN_SHELF_HRS>0</MIN_SHELF_HRS>
       <RULE_NAM></RULE_NAM>
       <PRT_CLIENT_ID>CLIENT A</PRT_CLIENT_ID>
       <INV_ATTR_STR1></INV_ATTR_STR1>
       <INV_ATTR_STR2></INV_ATTR_STR2>
       <INV_ATTR_STR3></INV_ATTR_STR3>
       <INV_ATTR_STR4></INV_ATTR_STR4>
       <INV_ATTR_STR5></INV_ATTR_STR5>
       <INV_ATTR_STR6></INV_ATTR_STR6>
       <INV_ATTR_STR7></INV_ATTR_STR7>
       <INV_ATTR_STR8></INV_ATTR_STR8>
       <INV_ATTR_STR9></INV_ATTR_STR9>
       <INV_ATTR_STR10></INV_ATTR_STR10>
       <INV_ATTR_STR11></INV_ATTR_STR11>
       <INV_ATTR_STR12></INV_ATTR_STR12>
       <INV_ATTR_STR13></INV_ATTR_STR13>
       <INV_ATTR_STR14></INV_ATTR_STR14>
       <INV_ATTR_STR15></INV_ATTR_STR15>
       <INV_ATTR_STR16></INV_ATTR_STR16>
       <INV_ATTR_STR17></INV_ATTR_STR17>
       <INV_ATTR_STR18></INV_ATTR_STR18>
       <INV_ATTR_INT1></INV_ATTR_INT1>
       <INV_ATTR_INT2></INV_ATTR_INT2>
       <INV_ATTR_INT3></INV_ATTR_INT3>
       <INV_ATTR_INT4></INV_ATTR_INT4>
       <INV_ATTR_INT5></INV_ATTR_INT5>
       <INV_ATTR_FLT1></INV_ATTR_FLT1>
       <INV_ATTR_FLT2></INV_ATTR_FLT2>
       <INV_ATTR_FLT3></INV_ATTR_FLT3>
       <INV_ATTR_DTE1></INV_ATTR_DTE1>
       <INV_ATTR_DTE1_FMT></INV_ATTR_DTE1_FMT>
       <INV_ATTR_DTE1_FMTVAL></INV_ATTR_DTE1_FMTVAL>
       <INV_ATTR_DTE2></INV_ATTR_DTE2>
       <INV_ATTR_DTE2_FMT></INV_ATTR_DTE2_FMT>
       <INV_ATTR_DTE2_FMTVAL></INV_ATTR_DTE2_FMTVAL>
       <CSTMS_TYP></CSTMS_TYP>
       <CSTMS_VAT_COD></CSTMS_VAT_COD>
       <CSTMS_CMMDTY_COD></CSTMS_CMMDTY_COD>
       <DFLT_ORGCOD></DFLT_ORGCOD>
       <DTY_STMP_TRK_FLG>0</DTY_STMP_TRK_FLG>
       <CSTMS_CST></CSTMS_CST>
       <CSTMS_CRNCY></CSTMS_CRNCY>
       <ABS_ORDINV_WIN></ABS_ORDINV_WIN>
       <ABS_ORDINV_CODE></ABS_ORDINV_CODE>
       <LINE_SEG>
         <SEGNAM>LINE_SEG</SEGNAM>
         <BOMLIN>0001</BOMLIN>
         <PRTNUM>CYC_EA_PRT2</PRTNUM>
         <REVLVL></REVLVL>
         <LOTNUM></LOTNUM>
         <SUP_LOTNUM></SUP_LOTNUM>
         <ORGCOD></ORGCOD>
         <HSTSTS></HSTSTS>
         <CNSQTY>2</CNSQTY>
         <UNTCAS>0</UNTCAS>
         <UNTPAK>0</UNTPAK>
         <SKP_ALC_FLG>0</SKP_ALC_FLG>
         <CNS_TOL_PCT></CNS_TOL_PCT>
         <OVRCOD></OVRCOD>
         <OVRAMT>0</OVRAMT>
         <RPQFLG>0</RPQFLG>
         <XDKFLG>0</XDKFLG>
         <INVSTS>A</INVSTS>
         <INVSTS_PRG>A</INVSTS_PRG>
         <CNS_CATCH_QTY>0</CNS_CATCH_QTY>
         <ALLOCATE_CATCH>0</ALLOCATE_CATCH>
         <SUPNUM></SUPNUM>
         <PRCLOC></PRCLOC>
         <FTPCOD></FTPCOD>
         <ORDINV></ORDINV>
         <MIN_SHELF_HRS></MIN_SHELF_HRS>
         <PRT_CLIENT_ID>CLIENT A</PRT_CLIENT_ID>
         <EXP_SCP></EXP_SCP>
         <RULE_NAM></RULE_NAM>
         <MANDTE></MANDTE>
         <EXPIRE_DTE></EXPIRE_DTE>
         <MANDTE_FMT></MANDTE_FMT>
         <MANDTE_FMTVAL></MANDTE_FMTVAL>
         <EXPIRE_DTE_FMT></EXPIRE_DTE_FMT>
         <EXPIRE_DTE_FMTVAL></EXPIRE_DTE_FMTVAL>
         <INV_ATTR_STR1></INV_ATTR_STR1>
         <INV_ATTR_STR2></INV_ATTR_STR2>
         <INV_ATTR_STR3></INV_ATTR_STR3>
         <INV_ATTR_STR4></INV_ATTR_STR4>
         <INV_ATTR_STR5></INV_ATTR_STR5>
         <INV_ATTR_STR6></INV_ATTR_STR6>
         <INV_ATTR_STR7></INV_ATTR_STR7>
         <INV_ATTR_STR8></INV_ATTR_STR8>
         <INV_ATTR_STR9></INV_ATTR_STR9>
         <INV_ATTR_STR10></INV_ATTR_STR10>
         <INV_ATTR_STR11></INV_ATTR_STR11>
         <INV_ATTR_STR12></INV_ATTR_STR12>
         <INV_ATTR_STR13></INV_ATTR_STR13>
         <INV_ATTR_STR14></INV_ATTR_STR14>
         <INV_ATTR_STR15></INV_ATTR_STR15>
         <INV_ATTR_STR16></INV_ATTR_STR16>
         <INV_ATTR_STR17></INV_ATTR_STR17>
         <INV_ATTR_STR18></INV_ATTR_STR18>
         <INV_ATTR_INT1></INV_ATTR_INT1>
         <INV_ATTR_INT2></INV_ATTR_INT2>
         <INV_ATTR_INT3></INV_ATTR_INT3>
         <INV_ATTR_INT4></INV_ATTR_INT4>
         <INV_ATTR_INT5></INV_ATTR_INT5>
         <INV_ATTR_FLT1></INV_ATTR_FLT1>
         <INV_ATTR_FLT2></INV_ATTR_FLT2>
         <INV_ATTR_FLT3></INV_ATTR_FLT3>
         <INV_ATTR_DTE1></INV_ATTR_DTE1>
         <INV_ATTR_DTE1_FMT></INV_ATTR_DTE1_FMT>
         <INV_ATTR_DTE1_FMTVAL></INV_ATTR_DTE1_FMTVAL>
         <INV_ATTR_DTE2></INV_ATTR_DTE2>
         <INV_ATTR_DTE2_FMT></INV_ATTR_DTE2_FMT>
         <INV_ATTR_DTE2_FMTVAL></INV_ATTR_DTE2_FMTVAL>
         <ABS_ORDINV_WIN></ABS_ORDINV_WIN>
         <ABS_ORDINV_CODE></ABS_ORDINV_CODE>
       </LINE_SEG>
       <PRCS_SEG>
         <SEGNAM>PRCS_SEG</SEGNAM>
         <WKO_TYP>ASMBLE</WKO_TYP>
         <PRCARE>LINE</PRCARE>
         <PRDLIN></PRDLIN>
         <DISASS_PRCLOC></DISASS_PRCLOC>
         <NUM_PEOPLE></NUM_PEOPLE>
         <SPEED></SPEED>
         <ACTCOD></ACTCOD>
         <DEF_GEN_FLG>1</DEF_GEN_FLG>
       </PRCS_SEG>
    </HEADER_SEG>
  </CTRL_SEG>
</BOM_INB_IFD> 